packagepaul/__init__.py
packagepaul/main.py
packagepaul-0.1.2.dist-info/METADATA
packagepaul-0.1.2.dist-info/WHEEL
packagepaul-0.1.2.dist-info/RECORD
